{
  "words": [
    "Jobs",
    "Mo'Steel",
    "Earth",
    "Rock",
    "Mark",
    "Chapter",
    "D-Caf",
    "Mayflower",
    "Billy",
    "The",
    "Cordelia",
    "Face",
    "Yago",
    "Jobs's",
    "Hoyle",
    "Marine",
    "Willett",
    "Pipe",
    "Weir",
    "Mo'Steel's",
    "San",
    "Francisco",
    "Tamara",
    "Duck",
    "Cordelia's",
    "Marines",
    "Melman",
    "Big",
    "Bill",
    "I'm",
    "Miami",
    "Andreeson",
    "Hamster",
    "Eighty",
    "Edward",
    "Project",
    "I'll",
    "Boxer",
    "Florida",
    "You",
    "Mark's",
    "Mom",
    "Web",
    "Hwang",
    "States",
    "Bay",
    "California",
    "New",
    "York",
    "Ocean",
    "Kennedy",
    "Sink",
    "Harlin",
    "God",
    "Jane",
    "Agent",
    "Houston",
    "United",
    "Secret",
    "Service",
    "Corps",
    "Huerta",
    "Mars",
    "Jupiter",
    "Libertad",
    "Texas",
    "One",
    "Stereo",
    "All",
    "I've",
    "WebboScreed",
    "Space",
    "Center",
    "Mother",
    "D-Caf's",
    "Shy",
    "Europa",
    "Hey",
    "Yago's",
    "Area",
    "English",
    "Colonel",
    "Prologue",
    "Romans",
    "American",
    "Ford",
    "Monterey",
    "Highway",
    "Wal-Mart",
    "Pacific",
    "Molly",
    "Folly",
    "White",
    "House",
    "Jennifer",
    "Six",
    "Flags",
    "Colorado",
    "Systems",
    "Gonzalez",
    "Man",
    "Steel",
    "Yeah",
    "Data",
    "Security",
    "Agency",
    "His",
    "Austin",
    "Billy's",
    "It's",
    "Thanks",
    "There's",
    "Asian",
    "Essence",
    "Carl",
    "Face's",
    "What",
    "Suburban",
    "Cape",
    "Canaveral",
    "Paul",
    "Baltimore",
    "Krispy",
    "Robert",
    "Castleman",
    "There",
    "Horvath",
    "Jackson",
    "Band-Aid",
    "Twin",
    "Peaks",
    "Lucy",
    "Golden",
    "Gate",
    "Bridge",
    "Alameda",
    "Sergeant",
    "Connie",
    "Maybe",
    "Dad",
    "Lord",
    "Little",
    "Africa",
    "Mylar",
    "Earth's",
    "Spain",
    "Atlantic",
    "Hannibal's",
    "Carthaginian",
    "Varro",
    "Canae",
    "Abraham",
    "Lincoln",
    "Indiana",
    "Montana",
    "Carmel",
    "Silicon",
    "Valley",
    "Palo",
    "Alto",
    "Saturday",
    "Turn",
    "Operation",
    "This",
    "James",
    "Dean",
    "Ford's",
    "Car",
    "Destination",
    "South",
    "Global",
    "Positioning",
    "System",
    "Beetle",
    "Sebastian",
    "Steven",
    "Sound",
    "Green",
    "Day",
    "Search",
    "Didn't",
    "Can",
    "Soar",
    "Hondo",
    "Ever",
    "Previous",
    "Times",
    "Play",
    "Noah's",
    "Ark",
    "Professor",
    "Stanford",
    "Call",
    "Denver",
    "Skateboggan",
    "Teflon",
    "Mount",
    "Cisco",
    "Express",
    "Launch",
    "Point",
    "Romeo",
    "More",
    "Answer",
    "Let",
    "City",
    "Maryland",
    "Oono",
    "Inc",
    "Swiss",
    "Ham",
    "Dad's",
    "They",
    "Rings",
    "Part",
    "Watcher",
    "Nice",
    "Homo",
    "Ludmillas'",
    "Chernokozovo",
    "Chechnya",
    "Ruslan",
    "Russians",
    "Weirs",
    "William",
    "Weird",
    "Russian",
    "Jessica",
    "Holy",
    "Terror",
    "Week",
    "Texas-style",
    "Bill's",
    "Spider-Man",
    "Bulgari",
    "Pink",
    "Austen",
    "Skirts",
    "Techie",
    "Cordy's",
    "That's",
    "Essie",
    "WaterBaby",
    "Chinese",
    "Daddy",
    "Has",
    "Mommy",
    "Ramirez",
    "Dawn",
    "Schulz-Hwang",
    "Long",
    "Island",
    "Special",
    "Mongol",
    "Old",
    "Navy",
    "Andreeson's",
    "T-shirts",
    "For",
    "God's",
    "Jen",
    "Digit's",
    "Officially",
    "Airport",
    "Jose",
    "Seattle",
    "Boston",
    "Washington",
    "Defense",
    "Department",
    "Baltimore-Washington",
    "International",
    "Aware",
    "Individuals",
    "Kreme",
    "Their",
    "Ruger",
    "Kremes",
    "President",
    "Janice",
    "Chelsea",
    "Clinton",
    "Perfect",
    "Presidential",
    "Children",
    "Amy",
    "Carter",
    "John-John",
    "Lincoln's",
    "Gun",
    "Azerbaijan",
    "Death",
    "Nature",
    "Caucasian",
    "African-American",
    "Democrats",
    "Republicans",
    "Literally",
    "Stop",
    "Earanium",
    "Rock's",
    "Everyone",
    "Show",
    "Beluga",
    "Lucy's",
    "Psycho",
    "Rebecca",
    "Sorry",
    "Oakland",
    "Protect",
    "Iwo",
    "Jima",
    "Inchon",
    "Sarge",
    "Tokyo",
    "I'd",
    "Tamara's",
    "Doctor",
    "Titusville",
    "Just",
    "Pebble",
    "Edward's",
    "Bobby",
    "Dallas",
    "Cowboys",
    "T-shirt",
    "Spanish",
    "People",
    "Starbucks",
    "Kingdom",
    "Bless",
    "America",
    "Americans",
    "I-beams",
    "Plexiglas-topped",
    "Kind",
    "Plexiglas",
    "Jasper",
    "Look",
    "Hoyle's",
    "Marine's",
    "Tom's",
    "West",
    "DCaf",
    "Get",
    "Don't",
    "Captain",
    "Gates",
    "Boole",
    "Eckert",
    "Shastri",
    "Mo's",
    "Take",
    "Commander",
    "Willett's",
    "Portugal",
    "Connecticut",
    "Iberian",
    "Mediterranean",
    "Sea",
    "France",
    "Italy",
    "Balkans",
    "Greece",
    "Turkey",
    "Israel",
    "Western",
    "Rome",
    "Cairo",
    "Athens",
    "Barcelona",
    "Istanbul",
    "Jerusalem",
    "Damascus",
    "Charleston",
    "Appalachian",
    "Mountain",
    "Grand",
    "Canyons"
  ],
  "phonetics": {
    "Cordelia": "kordeeleeya",
    "Yago": "yahgoh",
    "Jobs's": "jobziz",
    "Francisco": "fransiskoh",
    "Cordelia's": "kordeeleeyaz",
    "Miami": "myamee",
    "Andreeson": "andreesehn",
    "Hwang": "wahng",
    "California": "kalifornya",
    "Ocean": "ohshen",
    "Mo'Steel's": "mohsteelz",
    "Kennedy": "kenuhdee",
    "Houston": "hyoostun",
    "Corps": "core",
    "Huerta": "wairtuh",
    "Libertad": "leebairtahd",
    "One": "wun",
    "I've": "ive",
    "WebboScreed": "webohscreed",
    "D-Caf's": "deekafs",
    "Europa": "yoorohpuh",
    "Yago's": "yahgohz",
    "Colonel": "kernul",
    "Monterey": "montuhray",
    "Wal-Mart": "wawlmart",
    "Gonzalez": "gonzahlez",
    "Yeah": "yeh",
    "Data": "daytuh",
    "Asian": "ayzhun",
    "What": "wot",
    "Canaveral": "kuhnaverul",
    "Baltimore": "bawltimor",
    "Horvath": "horvath",
    "Band-Aid": "bandayd",
    "Alameda": "alamayduh",
    "Sergeant": "sarjunt",
    "Hannibal's": "hanibuls",
    "Carthaginian": "karthuhjinyun",
    "Varro": "varoh",
    "Canae": "kuhnay",
    "Abraham": "aybruhham",
    "Lincoln": "linkin",
    "Indiana": "indeeana",
    "Carmel": "karmel",
    "Silicon": "sillikon",
    "Palo": "pahloh",
    "Alto": "altoh",
    "Beetle": "beetul",
    "Sebastian": "sebastyan",
    "Hondo": "hondoh",
    "Noah's": "nohuz",
    "Cisco": "siskoh",
    "Answer": "anser",
    "Ludmillas'": "loodmillas",
    "Chernokozovo": "churnokozovo",
    "Weirs": "weers",
    "Bulgari": "boolgari",
    "Austen": "awsten",
    "Ramirez": "rahmeerezz",
    "Schulz-Hwang": "shooltswahng",
    "Island": "eyeland",
    "Andreeson's": "andreesons",
    "T-shirts": "teeshirts",
    "Jose": "hohzey",
    "Seattle": "seeattel",
    "Washington": "woshington",
    "Baltimore-Washington": "baltimorwoshington",
    "Kreme": "kreem",
    "Ruger": "rooger",
    "Kremes": "kreems",
    "Chelsea": "chelsee",
    "John-John": "jonjon",
    "Azerbaijan": "ahzerbyejan",
    "Caucasian": "kawkayzhun",
    "African-American": "africanamerican",
    "Earanium": "eereynium",
    "Beluga": "buhlooguh",
    "Psycho": "sykoh",
    "Iwo": "eewoh",
    "Jima": "jeemuh",
    "Inchon": "inchon",
    "Tokyo": "tohkyoh",
    "Tamara's": "tuhmahraaz",
    "Titusville": "tytusvil",
    "T-shirt": "teeshirt",
    "I-beams": "eebems",
    "Plexiglas-topped": "pleksiglasstopt",
    "Plexiglas": "pleksiglass",
    "DCaf": "deekaf",
    "Boole": "bool",
    "Eckert": "ekert",
    "Shastri": "shahstree",
    "Mo's": "moze",
    "Portugal": "porchuhgull",
    "Connecticut": "kuhnetikut",
    "Iberian": "eyebereean",
    "Mediterranean": "mediterayneean",
    "Balkans": "bawlkans",
    "Israel": "izrayel",
    "Cairo": "keyeroh",
    "Athens": "athenz",
    "Barcelona": "barsuhloana",
    "Istanbul": "istahnbool",
    "Jerusalem": "jerroosuhlem",
    "Damascus": "duhmaskus",
    "Appalachian": "apuhlaychun"
  }
}